dimple/__init__.py
pydimple/__init__.py
pydimple/funs.py
pydimple-0.1.dist-info/LICENSE
pydimple-0.1.dist-info/METADATA
pydimple-0.1.dist-info/WHEEL
pydimple-0.1.dist-info/top_level.txt
pydimple-0.1.dist-info/RECORD
