Metadata-Version: 2.1
Name: pydimple
Version: 0.1
Summary: Proof-of-concept implementation of dimple (debiased inference made simple)
Author: Alex Luedtke
Author-email: aluedtke@uw.edu
License: MIT
Requires-Python: >=3.8
License-File: LICENSE
Requires-Dist: numpy
Requires-Dist: pandas
Requires-Dist: scipy
Requires-Dist: scikit-learn
Requires-Dist: optuna ==3.2.0
Requires-Dist: lightgbm ==3.3.5
Requires-Dist: sympy
Requires-Dist: statsmodels
